thingy.py
Thingy-0.10.0.dist-info/LICENSE
Thingy-0.10.0.dist-info/METADATA
Thingy-0.10.0.dist-info/WHEEL
Thingy-0.10.0.dist-info/top_level.txt
Thingy-0.10.0.dist-info/RECORD
