Metadata-Version: 2.1
Name: Thingy
Version: 0.10.0
Summary: Dictionary as an object, that can have different views
Home-page: https://github.com/Refty/thingy
Author: Guillaume Gelin
Author-email: guillaume@refty.co
License: MIT
Platform: any
Classifier: Intended Audience :: Developers
Classifier: Operating System :: OS Independent
Classifier: Programming Language :: Python
Classifier: Topic :: Software Development :: Libraries :: Python Modules
License-File: LICENSE
